autogon_internal/__init__.py
autogon_internal/autoClassification/__init__.py
autogon_internal/autoClassification/base.py
autogon_internal/autoFeatureEngineering/__init__.py
autogon_internal/autoFeatureEngineering/base.py
autogon_internal/autoRegression/__init__.py
autogon_internal/autoRegression/base.py
autogonML-1.0.1.dist-info/METADATA
autogonML-1.0.1.dist-info/WHEEL
autogonML-1.0.1.dist-info/top_level.txt
autogonML-1.0.1.dist-info/RECORD
